LICENSE
MANIFEST.in
README.md
setup.py
ttext/__init__.py
ttext/autolink.py
ttext/extractor.py
ttext/highlighter.py
ttext/regex.py
ttext/unicode.py
ttext/validation.py
ttext.egg-info/PKG-INFO
ttext.egg-info/SOURCES.txt
ttext.egg-info/dependency_links.txt
ttext.egg-info/requires.txt
ttext.egg-info/top_level.txt
ttext/templatetags/__init__.py
ttext/templatetags/twitterize.py