Metadata-Version: 1.1
Name: ttext
Version: 0.0.1
Summary: A library for auto-converting URLs, mentions, hashtags, lists, etc. in Twitter text. Also does tweet validation and search term highlighting.
Home-page: https://github.com/BigPropeller/ttext
Author: Gain App
Author-email: developers@gainapp.com
License: MIT
Platform: UNKNOWN
Classifier: Development Status :: 5 - Production/Stable
Classifier: Environment :: Web Environment
Classifier: Intended Audience :: Developers
Classifier: License :: OSI Approved :: MIT License
Classifier: Operating System :: OS Independent
Classifier: Programming Language :: Python :: 2.7
Classifier: Programming Language :: Python :: 3
Classifier: Programming Language :: Python :: 3.4
Classifier: Programming Language :: Python :: 3.5
Classifier: Programming Language :: Python :: 3.6
